db_log/__init__.py
db_log/admin.py
db_log/apps.py
db_log/handlers.py
db_log/models.py
db_log/tests.py
db_log/views.py
db_log/migrations/0001_initial.py
db_log/migrations/0002_auto_20190322_2139.py
db_log/migrations/0003_auto_20190323_0207.py
db_log/migrations/__init__.py
db_loghandler/__init__.py
db_loghandler/admin.py
db_loghandler/apps.py
db_loghandler/handlers.py
db_loghandler/models.py
db_loghandler/tests.py
db_loghandler/views.py
db_loghandler/migrations/0001_initial.py
db_loghandler/migrations/__init__.py
django_db_loghandler-0.0.7.dist-info/LICENSE
django_db_loghandler-0.0.7.dist-info/METADATA
django_db_loghandler-0.0.7.dist-info/WHEEL
django_db_loghandler-0.0.7.dist-info/top_level.txt
django_db_loghandler-0.0.7.dist-info/RECORD
