Metadata-Version: 2.1
Name: django-db-loghandler
Version: 0.0.7
Summary: Logging handler for Django Database
Home-page: UNKNOWN
Author: Jonghak Choi
Author-email: haginara@gmail.com
License: UNKNOWN
Platform: UNKNOWN
Classifier: Intended Audience :: Developers
Classifier: License :: OSI Approved :: BSD License
Classifier: Operating System :: OS Independent
Classifier: Programming Language :: Python
Classifier: Programming Language :: Python :: 3.6
Classifier: Programming Language :: Python :: 3.7
Classifier: Programming Language :: Python
Classifier: Topic :: Software Development :: Libraries :: Python Modules
Requires-Dist: django (>=1.2.7)
